house_prices/__init__.py
house_prices/inference.py
house_prices/preprocess.py
house_prices/train.py
house_prices_gst-0.0.2.dist-info/LICENSE.txt
house_prices_gst-0.0.2.dist-info/METADATA
house_prices_gst-0.0.2.dist-info/WHEEL
house_prices_gst-0.0.2.dist-info/top_level.txt
house_prices_gst-0.0.2.dist-info/RECORD
