Metadata-Version: 2.1
Name: house-prices-gst
Version: 0.0.2
Summary: Data Science in Production
Home-page: https://github.com/GuitooStephan/dsp-stephane-tanoh
Author: Stephane Tanoh
Author-email: guystephane00@gmail.com
License: UNKNOWN
Project-URL: Bug Tracker, https://github.com/GuitooStephan/dsp-stephane-tanoh/issues
Platform: UNKNOWN
Classifier: Programming Language :: Python :: 3
Classifier: License :: OSI Approved :: MIT License
Classifier: Operating System :: OS Independent
Requires-Python: >=3.6
License-File: LICENSE.txt
Requires-Dist: pandas
Requires-Dist: scikit-learn
Requires-Dist: scipy
Requires-Dist: joblib
